{"order_uid":"01HB13R8185R6K8K3YGN11S1P2","Track_number":"01HB13R818S8DPDWM2NNDJA491","entry":"01HB13R819Z68PRRG30EN6RNXS","locale":"01HB13R819FDJ5SFMBKRQGNZH0","internal_signature":"01HB13R819BG37E1JHFZRB9F9Y","customer_id":"01HB13R819A97ZZKR5J07CMG61","delivery_service":"01HB13R819WQ347FB9PC7XT8GK","shardkey":"01HB13R819MNZK5RV8X3A6NQWY","sm_id":645,"date_created":"2022-12-15T11:33:59Z","oof_shard":"01HB13R8191B01PGZFBW99545C","delivery":{"name":"Eleen Leve","phone":"+7 839 203 0015","zip":"01HB13R81AJFAMTFAD08R5G7WV","city":"Pushkino","address":"8366 Southridge Hill","region":"KE-700","email":"elevecd@cbsnews.com"},"items":[{"chrt_id":44885,"track_number":"01HB13R818S8DPDWM2NNDJA491","price":8145,"rid":"01HB13R81BHNWKCZNT361NTVA1","name":"Largeflower Phacelia","sale":1,"size":"S","total_price":8063,"nm_id":1644,"brand":"Hydrocortisone","status":972},{"chrt_id":130699,"track_number":"01HB13R818S8DPDWM2NNDJA491","price":2895,"rid":"01HB13R81CBB8GQDAAW3ZNNWB7","name":"Greater Yellow Lady's Slipper","sale":52,"size":"XL","total_price":1389,"nm_id":5832,"brand":"RIVASTIGMINE TARTRATE","status":122},{"chrt_id":433882,"track_number":"01HB13R818S8DPDWM2NNDJA491","price":7031,"rid":"01HB13R81EV607MHZV2YQHH19W","name":"Decodon","sale":53,"size":"2XL","total_price":3304,"nm_id":5763,"brand":"PhysiciansCare Cold and Cough","status":42},{"chrt_id":721521,"track_number":"01HB13R818S8DPDWM2NNDJA491","price":586,"rid":"01HB13R81GD6M66NBP70VZ4FV3","name":"Hornwort","sale":84,"size":"XL","total_price":93,"nm_id":5971,"brand":"Hydrocortisone","status":516},{"chrt_id":110578,"track_number":"01HB13R818S8DPDWM2NNDJA491","price":9296,"rid":"01HB13R81JY88F07WYHNADTWX3","name":"Amaryllis","sale":53,"size":"XL","total_price":4369,"nm_id":5246,"brand":"Budesonide","status":75}],"payment":{"transaction":"01HB13R8185R6K8K3YGN11S1P2","request_id":"01HB13R81KN28FHK0EPYA81AF4","currency":"Ruble","provider":"01HB13R81K7K19PTW0KEZQ9GKH","payment_dt":9223107,"delivery_cost":1901,"bank":"MU70 DQTC 8489 2750 9301 6691 186C QJ","custom_fee":6887,"goods_total":17218,"amount":26006}}