{"order_uid":"01HB13R94T7B73RMZV3Q8E7QF7","Track_number":"01HB13R94V685E6HE550GB03FG","entry":"01HB13R94VQW2988W1RTP4CBZ6","locale":"01HB13R94V842NFTXMH7SDDVTT","internal_signature":"01HB13R94VMMJW84XKGBXC524Y","customer_id":"01HB13R94VJATWTXGNSNCGT5YW","delivery_service":"01HB13R94V2NJBR68N259RWXQG","shardkey":"01HB13R94VT779QNCAQV6GYWSA","sm_id":486,"date_created":"2022-11-16T09:32:11Z","oof_shard":"01HB13R94W9X288PTVP4M5JZAT","delivery":{"name":"Tiffanie Collman","phone":"+66 425 766 6589","zip":"01HB13R94WVCBEY8SWSA9F6WBW","city":"Lam Plai Mat","address":"63 Monterey Way","region":"ST-S","email":"tcollmanei@amazon.co.uk"},"items":[{"chrt_id":78136,"track_number":"01HB13R94V685E6HE550GB03FG","price":9483,"rid":"01HB13R94XP2JVW4J2PEVD07C2","name":"Fen Grass Of Parnassus","sale":82,"size":"M","total_price":1706,"nm_id":7930,"brand":"Imipramine Hydrochloride","status":591}],"payment":{"transaction":"01HB13R94T7B73RMZV3Q8E7QF7","request_id":"01HB13R94YB3TVNFP86280RT9P","currency":"Baht","provider":"01HB13R94Y5ZHPBAJHCA9D7DPP","payment_dt":8418140,"delivery_cost":187,"bank":"LB31 5625 K9VP TQHU HBUX RM7V OLTC","custom_fee":1756,"goods_total":1706,"amount":3649}}