{"order_uid":"01HB13R8KNMCFHNCQXVZATPB6F","Track_number":"01HB13R8KN5SN3D351WNQC73HS","entry":"01HB13R8KN84HCDWZD1F47RSW4","locale":"01HB13R8KNBJ07JWGME60SRNHD","internal_signature":"01HB13R8KN4DZTW6G1SR8X2CVP","customer_id":"01HB13R8KNVYRFPS7TDNHNVSG2","delivery_service":"01HB13R8KNV32FP00N1915JKJ0","shardkey":"01HB13R8KPCNFM9Z3M1F921JMZ","sm_id":130,"date_created":"2022-12-07T11:28:30Z","oof_shard":"01HB13R8KPCR06WC6Q80C8NFHR","delivery":{"name":"Corina Sennett","phone":"+86 166 669 2484","zip":"01HB13R8KP5EC92F28PTZX5RFQ","city":"Niulanshan","address":"801 Kingsford Crossing","region":"DM-02","email":"csennettd1@scribd.com"},"items":[{"chrt_id":145866,"track_number":"01HB13R8KN5SN3D351WNQC73HS","price":132,"rid":"01HB13R8KS6A2ZZ6XC4S13ZHWF","name":"New Mexico Thistle","sale":5,"size":"3XL","total_price":125,"nm_id":4868,"brand":"Protonix","status":363},{"chrt_id":565163,"track_number":"01HB13R8KN5SN3D351WNQC73HS","price":4174,"rid":"01HB13R8KWCY5CQ8Z51KN8JKGG","name":"Gulf Cockspur Grass","sale":91,"size":"M","total_price":375,"nm_id":8289,"brand":"Lisinopril","status":666},{"chrt_id":572039,"track_number":"01HB13R8KN5SN3D351WNQC73HS","price":9036,"rid":"01HB13R8KZWB93W9FACX469JKR","name":"Smooth Bedstraw","sale":22,"size":"2XL","total_price":7048,"nm_id":9485,"brand":"Colgate","status":21},{"chrt_id":337368,"track_number":"01HB13R8KN5SN3D351WNQC73HS","price":7048,"rid":"01HB13R8M3KXMNSFC3GBMV1R80","name":"Tropical Desert-thorn","sale":54,"size":"3XL","total_price":3242,"nm_id":9722,"brand":"Acetylcysteine","status":440}],"payment":{"transaction":"01HB13R8KNMCFHNCQXVZATPB6F","request_id":"01HB13R8M56DQ0KJ5ZSD8Z0RKX","currency":"Yuan Renminbi","provider":"01HB13R8M6RMHAWH05BAMEW18P","payment_dt":342231,"delivery_cost":839,"bank":"FR07 5171 8776 11SA U9XG JGE6 C97","custom_fee":1500,"goods_total":10790,"amount":13129}}