{"order_uid":"01HB13R621KRKEZB6F1145ATJZ","Track_number":"01HB13R621TN4YFAB59N9J9N1Q","entry":"01HB13R621K46JXVBZ3XKH6P91","locale":"01HB13R621JRKK48V4VQ640M5C","internal_signature":"01HB13R62291H2100H73XXBPGT","customer_id":"01HB13R6222CS3FN6ZH173NRGV","delivery_service":"01HB13R622BM9FVZEVP6YFAKS1","shardkey":"01HB13R622GQSTCCFP00JF7G98","sm_id":125,"date_created":"2022-01-01T18:23:42Z","oof_shard":"01HB13R622CK7WNFN5V5ZZ3YR3","delivery":{"name":"Hugues Sigert","phone":"+502 442 794 6343","zip":"01HB13R623DXMPDV8433MCBCF0","city":"Yupiltepeque","address":"7462 Onsgard Trail","region":"ID-PA","email":"hsigert7u@usa.gov"},"items":[{"chrt_id":505415,"track_number":"01HB13R621TN4YFAB59N9J9N1Q","price":6746,"rid":"01HB13R624T02GYTC0PQ768DBA","name":"Silverskin Lichen","sale":85,"size":"XS","total_price":1011,"nm_id":492,"brand":"Flunisolide","status":261},{"chrt_id":771348,"track_number":"01HB13R621TN4YFAB59N9J9N1Q","price":8510,"rid":"01HB13R625AM28EKRAK0EH5DK7","name":"Dust Lichen","sale":36,"size":"M","total_price":5446,"nm_id":8500,"brand":"ChapStick Hydration Lock Day and Night","status":866},{"chrt_id":849344,"track_number":"01HB13R621TN4YFAB59N9J9N1Q","price":4170,"rid":"01HB13R627TSWNK9A8ZHAZ8A8N","name":"Common Flax","sale":27,"size":"2XL","total_price":3044,"nm_id":7592,"brand":"Tekturna HCT","status":150},{"chrt_id":768547,"track_number":"01HB13R621TN4YFAB59N9J9N1Q","price":4495,"rid":"01HB13R629QCW60Y1V7S5GR0KK","name":"Mexican Flannelbush","sale":50,"size":"XS","total_price":2247,"nm_id":4699,"brand":"take cover anti-aging foundation","status":134},{"chrt_id":782984,"track_number":"01HB13R621TN4YFAB59N9J9N1Q","price":1166,"rid":"01HB13R62AJ1048RV7W2QE1JP7","name":"Megaspora Lichen","sale":69,"size":"3XL","total_price":361,"nm_id":2757,"brand":"Prilocaine Hydrochloride with Epinephrine","status":445}],"payment":{"transaction":"01HB13R621KRKEZB6F1145ATJZ","request_id":"01HB13R62B7ED05B42WJFKW2MD","currency":"Quetzal","provider":"01HB13R62CH0KK6WKH5GRJBJD5","payment_dt":73627,"delivery_cost":514,"bank":"FR89 7106 2267 86CQ LC7I ETHR 581","custom_fee":8965,"goods_total":12109,"amount":21588}}