{"order_uid":"01HB13RBHAQEK870VYY7S2C6AW","Track_number":"01HB13RBHBN6DV7782THWNR784","entry":"01HB13RBHB1G5HX5B189PED330","locale":"01HB13RBHBV9WKNGTCDM5FQNZH","internal_signature":"01HB13RBHB5KG9E6RFTZVVNA7W","customer_id":"01HB13RBHBYBRZM8TK728DZ1QZ","delivery_service":"01HB13RBHB8G5TS4ACM50JNGJB","shardkey":"01HB13RBHB0HQ5SA8EQ7QBSMN1","sm_id":956,"date_created":"2022-05-07T18:16:48Z","oof_shard":"01HB13RBHCAQ3VWDH8G17AQXKK","delivery":{"name":"Danette MacTrustie","phone":"+351 257 627 7732","zip":"01HB13RBHCBGYP4F52YACZ7P4D","city":"Cruzeiro","address":"32 Summerview Hill","region":"PK-BA","email":"dmactrustiek8@vk.com"},"items":[{"chrt_id":408912,"track_number":"01HB13RBHBN6DV7782THWNR784","price":9457,"rid":"01HB13RBHEGSRWS2KSPN3FZHMA","name":"Wolf's Currant","sale":31,"size":"L","total_price":6525,"nm_id":8329,"brand":"Oral-B Minute-Foam Mellow Mint","status":167}],"payment":{"transaction":"01HB13RBHAQEK870VYY7S2C6AW","request_id":"01HB13RBHF0Z6ZHN90EVEDKT95","currency":"Euro","provider":"01HB13RBHFJ0NJRM9R2NYA2WHN","payment_dt":2635188,"delivery_cost":926,"bank":"CR07 6747 1005 0153 1156 6","custom_fee":3569,"goods_total":6525,"amount":11020}}