{"order_uid":"01HB13R3B8MWBV50T91HR28JJW","Track_number":"01HB13R3B97R36PMYVKMWK0X8T","entry":"01HB13R3B9TBT99SMF4ZF952BD","locale":"01HB13R3B9PCV70QGRJBEHGB21","internal_signature":"01HB13R3B9ZZJMKN771H7GH45N","customer_id":"01HB13R3B9C7CC054BA1D6TWJV","delivery_service":"01HB13R3B9JMNTSRQ6W5A5VR82","shardkey":"01HB13R3B9SNV4TCQ67W13KT6N","sm_id":543,"date_created":"2022-07-11T14:42:40Z","oof_shard":"01HB13R3BA3PDCNDWBMRQWPJVP","delivery":{"name":"Jdavie Eayrs","phone":"+63 777 207 5675","zip":"01HB13R3BAJKCFMJVZ162K0R2Y","city":"Amucao","address":"1 Del Mar Junction","region":"RU-ORL","email":"jeayrs1f@aol.com"},"items":[{"chrt_id":165197,"track_number":"01HB13R3B97R36PMYVKMWK0X8T","price":4283,"rid":"01HB13R3BCKA9TC8EKT6VCERJF","name":"Baldwin's Spikerush","sale":12,"size":"XL","total_price":3769,"nm_id":403,"brand":"Retin-A","status":248},{"chrt_id":214255,"track_number":"01HB13R3B97R36PMYVKMWK0X8T","price":3371,"rid":"01HB13R3BDCFRYPXTW93BJ3Z38","name":"Broadbeard Beardtongue","sale":43,"size":"2XL","total_price":1921,"nm_id":3365,"brand":"Vermex","status":27},{"chrt_id":132106,"track_number":"01HB13R3B97R36PMYVKMWK0X8T","price":4743,"rid":"01HB13R3BFHQKD9Q00VFFA8CF9","name":"Myrtleleaf Peperomia","sale":48,"size":"XL","total_price":2466,"nm_id":6108,"brand":"Body","status":434},{"chrt_id":384293,"track_number":"01HB13R3B97R36PMYVKMWK0X8T","price":6940,"rid":"01HB13R3BGZA9XAAQ4Q0290B6P","name":"Brandegee's Desertparsley","sale":85,"size":"3XL","total_price":1041,"nm_id":2254,"brand":"ibuprofen","status":383}],"payment":{"transaction":"01HB13R3B8MWBV50T91HR28JJW","request_id":"01HB13R3BJQN3BJY72JCRQQT6R","currency":"Peso","provider":"01HB13R3BJP8J3SX4G1FX3YH5H","payment_dt":3884425,"delivery_cost":1441,"bank":"MU26 YHJT 1101 1024 7323 0857 498R NZ","custom_fee":8818,"goods_total":9197,"amount":19456}}