{"order_uid":"01HB13RCNXHZ4XX6VJ50MGZS55","Track_number":"01HB13RCNXC5RK9BKVRQTR7D2J","entry":"01HB13RCNX463D25VR2N0E4FHR","locale":"01HB13RCNY1SVT7M8FABXC3ZGN","internal_signature":"01HB13RCNY2CR3667EE5B0D6C3","customer_id":"01HB13RCNYNGDZ9E068ZGVDPAQ","delivery_service":"01HB13RCNYA1MY50G6HMB716QZ","shardkey":"01HB13RCNYQ4BES69CKJ3VZCFR","sm_id":625,"date_created":"2022-01-01T07:00:07Z","oof_shard":"01HB13RCNZZX3FCF185ZQFQTWM","delivery":{"name":"Rabbi Nutting","phone":"+57 149 566 4165","zip":"01HB13RCNZWP1DACAD2GH3HA9Z","city":"Palermo","address":"5 Nobel Place","region":"NG-OY","email":"rnuttingnh@virginia.edu"},"items":[{"chrt_id":329674,"track_number":"01HB13RCNXC5RK9BKVRQTR7D2J","price":1451,"rid":"01HB13RCP0FHBSHQ02VRBT44RZ","name":"Ragweed","sale":69,"size":"L","total_price":449,"nm_id":7417,"brand":"Labetalol HCL","status":767},{"chrt_id":278756,"track_number":"01HB13RCNXC5RK9BKVRQTR7D2J","price":8656,"rid":"01HB13RCP213G788MKFH2HQEB9","name":"Redcardinal","sale":43,"size":"XL","total_price":4933,"nm_id":9523,"brand":"Hydroxyzine Hydrochloride","status":108}],"payment":{"transaction":"01HB13RCNXHZ4XX6VJ50MGZS55","request_id":"01HB13RCP4TPBZNNHSFA9W0F3Z","currency":"Peso","provider":"01HB13RCP4CK8V7V9H8ARSVXB0","payment_dt":7123805,"delivery_cost":1572,"bank":"SK14 4438 8880 8682 2483 9546","custom_fee":9277,"goods_total":5382,"amount":16231}}