{"order_uid":"01HB13R6DB3TMN6FNNJ58ZCWKH","Track_number":"01HB13R6DBEGS2327KTC1EV0WE","entry":"01HB13R6DCHY6MHXQ743KJAEDW","locale":"01HB13R6DCRCQQC64C8ACD3JA4","internal_signature":"01HB13R6DCWPWV1X4Z2R72T5FJ","customer_id":"01HB13R6DC2B83YZ8BNY79J3NC","delivery_service":"01HB13R6DCYHCMAJYHRPGNRH5J","shardkey":"01HB13R6DCKRP1QDEMXPPT88SD","sm_id":555,"date_created":"2022-05-09T19:52:17Z","oof_shard":"01HB13R6DCFA1MGH06ET3SK9KN","delivery":{"name":"Cathleen Kun","phone":"+86 688 563 8321","zip":"01HB13R6DD73WAJCYW3T7VNR73","city":"Nanping","address":"31 Hoepker Crossing","region":"US-AK","email":"ckun8x@psu.edu"},"items":[{"chrt_id":264648,"track_number":"01HB13R6DBEGS2327KTC1EV0WE","price":2577,"rid":"01HB13R6DESG7TTEP4RJAZ73RR","name":"Mono Lake Lupine","sale":67,"size":"XS","total_price":850,"nm_id":8732,"brand":"EczeNil","status":957},{"chrt_id":47845,"track_number":"01HB13R6DBEGS2327KTC1EV0WE","price":6147,"rid":"01HB13R6DGGBS3V02VG7Y7MAY9","name":"Sesquehana Sandcherry","sale":64,"size":"XL","total_price":2212,"nm_id":4431,"brand":"Clonidine Hydrochloride","status":767},{"chrt_id":270729,"track_number":"01HB13R6DBEGS2327KTC1EV0WE","price":2852,"rid":"01HB13R6DHVKBS44XHME4N3C0V","name":"Pondweed","sale":71,"size":"XS","total_price":827,"nm_id":5187,"brand":"Match Perfection SPF 18","status":945},{"chrt_id":496068,"track_number":"01HB13R6DBEGS2327KTC1EV0WE","price":2162,"rid":"01HB13R6DJ3M893CGX0SJZJYEP","name":"Yellowspike Orchid","sale":90,"size":"M","total_price":216,"nm_id":8825,"brand":"GRAPE","status":158},{"chrt_id":721073,"track_number":"01HB13R6DBEGS2327KTC1EV0WE","price":1007,"rid":"01HB13R6DMD76M9KA925KHTN32","name":"Coolabah","sale":50,"size":"XS","total_price":503,"nm_id":3048,"brand":"CD DiorSkin Forever Flawless Perfection Fusion Wear Makeup SPF 25 - 021","status":726}],"payment":{"transaction":"01HB13R6DB3TMN6FNNJ58ZCWKH","request_id":"01HB13R6DN31R4BVEDX13MHZ9T","currency":"Yuan Renminbi","provider":"01HB13R6DPERSCE79CQXQVH03K","payment_dt":3541150,"delivery_cost":1583,"bank":"FR65 8529 6355 00XZ VNJP TBF3 T15","custom_fee":478,"goods_total":4608,"amount":6669}}