{"order_uid":"01HB13R9TCWSFHESS187S8B28X","Track_number":"01HB13R9TC82HPNVZDF83K85N2","entry":"01HB13R9TCGJJDJ0GF77WT8GD4","locale":"01HB13R9TCCZ8QJBSBV3G81856","internal_signature":"01HB13R9TCYJGE09MFPC5G4QXP","customer_id":"01HB13R9TCYMG7C9SS3152BN35","delivery_service":"01HB13R9TCEWCB34E5ZMS7F2B1","shardkey":"01HB13R9TC3RS7E5FSSXK2Y571","sm_id":174,"date_created":"2022-11-27T07:33:48Z","oof_shard":"01HB13R9TD90EFRMRC7Q10HHW8","delivery":{"name":"Della Lorryman","phone":"+54 280 988 7049","zip":"01HB13R9TDJNR7XCCSCSWYGMBZ","city":"Ciervo Petiso","address":"0637 Lien Plaza","region":"US-DE","email":"dlorrymangi@smugmug.com"},"items":[{"chrt_id":427930,"track_number":"01HB13R9TC82HPNVZDF83K85N2","price":7384,"rid":"01HB13R9TEKGG05ZCF0W4VTWXQ","name":"Gooseberryleaf Globemallow","sale":93,"size":"XL","total_price":516,"nm_id":7507,"brand":"Synaptol","status":207},{"chrt_id":9486,"track_number":"01HB13R9TC82HPNVZDF83K85N2","price":9378,"rid":"01HB13R9TF3HE791XGGV1EXHR5","name":"Tetraclea","sale":78,"size":"S","total_price":2063,"nm_id":7179,"brand":"Gabapentin","status":811},{"chrt_id":317028,"track_number":"01HB13R9TC82HPNVZDF83K85N2","price":2355,"rid":"01HB13R9THHAC6510777KFG9ZF","name":"Knotweed Spineflower","sale":14,"size":"XL","total_price":2025,"nm_id":9009,"brand":"MaxFe","status":781}],"payment":{"transaction":"01HB13R9TCWSFHESS187S8B28X","request_id":"01HB13R9TJVG7W3CKABGKH1MW2","currency":"Peso","provider":"01HB13R9TJFEXW6Z0AC1T4JGN0","payment_dt":8045775,"delivery_cost":859,"bank":"MT31 KMVN 4214 0MW4 WBR2 VD2G D7YR V7S","custom_fee":9202,"goods_total":4604,"amount":14665}}