{"order_uid":"01HB13RDDCG37TDFXFNBDXTYEA","Track_number":"01HB13RDDCF5C8WHD836GBFBE1","entry":"01HB13RDDC7YB2DMJQ7SAK78Q8","locale":"01HB13RDDCXD3KYPE1MWFH5CTK","internal_signature":"01HB13RDDCTHFA6XNS8599A52P","customer_id":"01HB13RDDCXNVKK20DXNPFZZZR","delivery_service":"01HB13RDDDEHJ646FJ1A5ZDP7X","shardkey":"01HB13RDDD7PSHCPBM4BMKT0FR","sm_id":845,"date_created":"2022-02-14T12:19:43Z","oof_shard":"01HB13RDDDGHZT5VE5J9ZCMD4G","delivery":{"name":"Yuri Sommersett","phone":"+234 809 793 4557","zip":"01HB13RDDDXZ8F10XMXP2AP8B2","city":"Hunkuyi","address":"02840 Meadow Ridge Street","region":"CN-13","email":"ysommersettpi@surveymonkey.com"},"items":[{"chrt_id":129998,"track_number":"01HB13RDDCF5C8WHD836GBFBE1","price":9232,"rid":"01HB13RDDF6AYDJSZJCDEBAQC0","name":"Blazing Star","sale":77,"size":"XL","total_price":2123,"nm_id":848,"brand":"MAGNESIA PHOSPHORICA","status":782},{"chrt_id":528299,"track_number":"01HB13RDDCF5C8WHD836GBFBE1","price":9834,"rid":"01HB13RDDG4NMNS93YV2N3P9H1","name":"Lake Tahoe Serpentweed","sale":93,"size":"L","total_price":688,"nm_id":6087,"brand":"Fluvastatin Sodium","status":415},{"chrt_id":51776,"track_number":"01HB13RDDCF5C8WHD836GBFBE1","price":5733,"rid":"01HB13RDDJG7NWM40P6F4YP0XQ","name":"Indian Paintbrush","sale":4,"size":"XL","total_price":5503,"nm_id":3119,"brand":"Alfuzosin Hydrochloride","status":598},{"chrt_id":962654,"track_number":"01HB13RDDCF5C8WHD836GBFBE1","price":932,"rid":"01HB13RDDKK7B79XJCYA5AP181","name":"Silver Vine","sale":0,"size":"3XL","total_price":932,"nm_id":7913,"brand":"Naprosyn","status":268},{"chrt_id":987356,"track_number":"01HB13RDDCF5C8WHD836GBFBE1","price":7390,"rid":"01HB13RDDNQ690CSP90D21P3GQ","name":"Woolly Cinquefoil","sale":9,"size":"L","total_price":6724,"nm_id":258,"brand":"Glyburide","status":411}],"payment":{"transaction":"01HB13RDDCG37TDFXFNBDXTYEA","request_id":"01HB13RDDPKQX3H40WWPA07SS2","currency":"Naira","provider":"01HB13RDDP10Q2VHJDQA28NS8H","payment_dt":4959302,"delivery_cost":227,"bank":"AE41 1315 7091 6116 5012 824","custom_fee":6566,"goods_total":15970,"amount":22763}}