{"order_uid":"01HB13R3J6BB0X78KGY9X2NGNN","Track_number":"01HB13R3J6AK02XGHFYZTBC406","entry":"01HB13R3J6787D39TAGVATQZYE","locale":"01HB13R3J68MF63NHNYZHMC61A","internal_signature":"01HB13R3J6WCEB9YEYZ369XSKB","customer_id":"01HB13R3J68Y1JFX7TJTS2XMHH","delivery_service":"01HB13R3J6T3HGB86943QCN049","shardkey":"01HB13R3J6DQ515ZAPBMDXGJHG","sm_id":20,"date_created":"2022-02-01T08:13:18Z","oof_shard":"01HB13R3J7SZXDKDCM0YXHH7NS","delivery":{"name":"Marta Cressingham","phone":"+1 215 197 4455","zip":"01HB13R3J8K8BWH058Y98W9E51","city":"Philadelphia","address":"8871 Sommers Trail","region":"SE-AC","email":"mcressingham20@ca.gov"},"items":[{"chrt_id":83962,"track_number":"01HB13R3J6AK02XGHFYZTBC406","price":7648,"rid":"01HB13R3J9K117R1Y2V6B5A4GA","name":"Stiff Yellow Flax","sale":34,"size":"3XL","total_price":5047,"nm_id":9391,"brand":"Crest Pro-Health","status":752},{"chrt_id":686389,"track_number":"01HB13R3J6AK02XGHFYZTBC406","price":2057,"rid":"01HB13R3JA9XF903KHCFCH2PAH","name":"Zinnia","sale":89,"size":"2XL","total_price":226,"nm_id":6102,"brand":"Ropinirole Hydrochloride","status":980},{"chrt_id":610637,"track_number":"01HB13R3J6AK02XGHFYZTBC406","price":3137,"rid":"01HB13R3JCBXY3JX7SEK8FZVFM","name":"Southern Dawnflower","sale":71,"size":"XS","total_price":909,"nm_id":5293,"brand":"Bio Placenta Phase","status":742},{"chrt_id":76388,"track_number":"01HB13R3J6AK02XGHFYZTBC406","price":6770,"rid":"01HB13R3JE0EV7PQZCZZKG1147","name":"Mexican Orange","sale":30,"size":"L","total_price":4739,"nm_id":4201,"brand":"Lithiumeel","status":480},{"chrt_id":120968,"track_number":"01HB13R3J6AK02XGHFYZTBC406","price":4737,"rid":"01HB13R3JGEVGN8XCGM8BB2C4V","name":"Slimpod Rush","sale":31,"size":"M","total_price":3268,"nm_id":9176,"brand":"Metoprolol succinate","status":342}],"payment":{"transaction":"01HB13R3J6BB0X78KGY9X2NGNN","request_id":"01HB13R3JHX0RF772G8A7ZWC9Z","currency":"Dollar","provider":"01HB13R3JHF48SVNJ36QJJ3635","payment_dt":6829122,"delivery_cost":1863,"bank":"LV22 IKVT QIH7 ICWD QQKY D","custom_fee":6187,"goods_total":14189,"amount":22239}}