{"order_uid":"01HB13RC7TBHSEFST5TDJKENDQ","Track_number":"01HB13RC7TNASJYVRXHCGXX7SC","entry":"01HB13RC7VFSRJ4ZZPZ3AJ7N8C","locale":"01HB13RC7V8219CDSXJ6H0JYZV","internal_signature":"01HB13RC7VHET8C6SS830P5HNT","customer_id":"01HB13RC7VXBMRCP8VVV83VSC8","delivery_service":"01HB13RC7V4G05YN5F036SW4PJ","shardkey":"01HB13RC7VFX68HX5GAY9JEJX8","sm_id":332,"date_created":"2022-03-31T10:13:08Z","oof_shard":"01HB13RC7V4KKACKNKPRSX6HXB","delivery":{"name":"Nancey Giacovelli","phone":"+505 685 267 6481","zip":"01HB13RC7WB11CKB8F5W82HHZZ","city":"El Realejo","address":"1657 Darwin Alley","region":"US-KY","email":"ngiacovellim5@discovery.com"},"items":[{"chrt_id":439465,"track_number":"01HB13RC7TNASJYVRXHCGXX7SC","price":3641,"rid":"01HB13RC7XPNRQ0FTVMDTGSBBA","name":"Subalpine Fleabane","sale":9,"size":"3XL","total_price":3313,"nm_id":8807,"brand":"Hesol Rim Jean-Aeck","status":339},{"chrt_id":74773,"track_number":"01HB13RC7TNASJYVRXHCGXX7SC","price":7477,"rid":"01HB13RC7Z9P7WRMW00A7VBHC8","name":"Siskiyou Phacelia","sale":88,"size":"3XL","total_price":897,"nm_id":5669,"brand":"Reprexain","status":917},{"chrt_id":310304,"track_number":"01HB13RC7TNASJYVRXHCGXX7SC","price":4621,"rid":"01HB13RC80T1KHJJ9GD8ZS73A3","name":"Bristly Hawkbit","sale":12,"size":"XS","total_price":4066,"nm_id":9876,"brand":"Tartar Control Plus","status":252},{"chrt_id":441227,"track_number":"01HB13RC7TNASJYVRXHCGXX7SC","price":7200,"rid":"01HB13RC82ZPCB1HS4NBSQ3T8X","name":"Cutleaf Coneflower","sale":94,"size":"L","total_price":432,"nm_id":3627,"brand":"Camilia","status":686}],"payment":{"transaction":"01HB13RC7TBHSEFST5TDJKENDQ","request_id":"01HB13RC83NG0JCAF1V8SA83N3","currency":"Cordoba","provider":"01HB13RC84T0B2KYAJS5XGYP7W","payment_dt":3809465,"delivery_cost":1230,"bank":"KZ51 2772 UPJW KDCM CAGR","custom_fee":7093,"goods_total":8708,"amount":17031}}